setup.py
createdate/__init__.py
createdate/config.ini
createdate/deal_file.py
createdate/test.xlsx
createdate.egg-info/PKG-INFO
createdate.egg-info/SOURCES.txt
createdate.egg-info/dependency_links.txt
createdate.egg-info/top_level.txt
createdate.egg-info/zip-safe