Metadata-Version: 1.1
Name: createdate
Version: 1.0.0
Summary: it is for person
Home-page: https://github.com
Author: jianzhong.zhou
Author-email: 1329870572@qq.com
License: MIT
Platform: UNKNOWN
Classifier: License :: OSI Approved :: MIT License
Classifier: Programming Language :: Python
Classifier: Intended Audience :: Developers
